tableclasses/__about__.py
tableclasses/__init__.py
tableclasses/dc.py
tableclasses/errs.py
tableclasses/py.typed
tableclasses/types.py
tableclasses/base/__init__.py
tableclasses/base/field.py
tableclasses/base/tabled.py
tableclasses/pandas/__init__.py
tableclasses/pandas/gen.py
tableclasses/pandas/tabled.py
tableclasses-0.1.0.dist-info/METADATA
tableclasses-0.1.0.dist-info/WHEEL
tableclasses-0.1.0.dist-info/licenses/LICENSE.txt
tableclasses-0.1.0.dist-info/RECORD
