Metadata-Version: 2.1
Name: tableclasses
Version: 0.1.0
Summary: Dataclasses for tabular data
Project-URL: Documentation, https://github.com/joshua-auchincloss/tableclasses#readme
Project-URL: Issues, https://github.com/joshua-auchincloss/tableclasses/issues
Project-URL: Source, https://github.com/joshua-auchincloss/tableclasses
Author-email: joshua-auchincloss <joshua.auchincloss@proton.me>
License-Expression: MIT
License-File: LICENSE.txt
Classifier: Development Status :: 4 - Beta
Classifier: Programming Language :: Python
Classifier: Programming Language :: Python :: 3.11
Classifier: Programming Language :: Python :: 3.12
Classifier: Programming Language :: Python :: Implementation :: CPython
Classifier: Programming Language :: Python :: Implementation :: PyPy
Requires-Python: >=3.10
Requires-Dist: beartype
Requires-Dist: pyarrow
Provides-Extra: pandas
Requires-Dist: pandas; extra == 'pandas'
Provides-Extra: test
Requires-Dist: coverage[toml]; extra == 'test'
Requires-Dist: pytest; extra == 'test'
Requires-Dist: pytest-cov; extra == 'test'
